Calculator/Calculator.py
Calculator/__init__.py
BasicCalculatorLinasPelVersion-0.1.1.dist-info/LICENSE.txt
BasicCalculatorLinasPelVersion-0.1.1.dist-info/METADATA
BasicCalculatorLinasPelVersion-0.1.1.dist-info/WHEEL
BasicCalculatorLinasPelVersion-0.1.1.dist-info/top_level.txt
BasicCalculatorLinasPelVersion-0.1.1.dist-info/RECORD
