Metadata-Version: 2.1
Name: BasicCalculatorLinasPelVersion
Version: 0.1.1
Summary: Calculator package
Author: LinasPel (Linas Peleckas)
Author-email: <peleckas.l@gmail.com>
License: MIT
Keywords: python,calculator,basic,calculation
Classifier: Development Status :: 1 - Planning
Classifier: Intended Audience :: Developers
Classifier: Programming Language :: Python :: 3
Classifier: Operating System :: Unix
Classifier: Operating System :: MacOS :: MacOS X
Classifier: Operating System :: Microsoft :: Windows
License-File: LICENSE.txt
